hopfield/__init__.py
hopfield/main.py
hopfield_memory-0.0.2.dist-info/LICENSE
hopfield_memory-0.0.2.dist-info/METADATA
hopfield_memory-0.0.2.dist-info/WHEEL
hopfield_memory-0.0.2.dist-info/top_level.txt
hopfield_memory-0.0.2.dist-info/RECORD
