Metadata-Version: 2.1
Name: hopfield-memory
Version: 0.0.2
Summary: A Hopfield Network for associative memory tasks, specifically focusing on retrieving images even when they are blurred or corrupted.
Home-page: https://github.com/GatikiML/Hopfield
Author: Gatiki/Vyom
Author-email: gatikiml@gmail.com
Project-URL: Bug Tracker, https://github.com/GatikiML/Hopfield/issues
Classifier: Programming Language :: Python :: 3
Classifier: License :: OSI Approved :: MIT License
Classifier: Operating System :: OS Independent
Requires-Python: >=3.6
License-File: LICENSE
